Metadata-Version: 1.0
Name: python-foneworx
Version: 0.1
Summary: Foneworx XML API library
Home-page: http://github.com/smn/python-foneworx
Author: Simon de Haan
Author-email: dev@praekeltfoundation.org
License: BSD
Platform: UNKNOWN
